qtrex/__init__.py
qtrex/config.py
qtrex/errors.py
qtrex/executor.py
qtrex/models.py
qtrex/renderer.py
qtrex/store.py
qtrex-0.1.0.dist-info/LICENSE
qtrex-0.1.0.dist-info/METADATA
qtrex-0.1.0.dist-info/WHEEL
qtrex-0.1.0.dist-info/top_level.txt
qtrex-0.1.0.dist-info/RECORD
