Metadata-Version: 2.1
Name: qtrex
Version: 0.1.0
Summary: Query template rendering and execution library
Author-email: Bradley Bonitatibus <bradleybonitatibus@gmail.com>
License: Apache-2.0
Project-URL: Documentation, https://github.com/bradleybonitatibus/qtrex
Project-URL: Homepage, https://github.com/bradleybonitatibus/qtrex
Project-URL: Repository, https://github.com/bradleybonitatibus/qtrex
Classifier: Development Status :: 1 - Planning
Classifier: License :: OSI Approved :: Apache Software License
Classifier: Intended Audience :: Developers
Classifier: Natural Language :: English
Classifier: Operating System :: MacOS
Classifier: Operating System :: Microsoft :: Windows
Classifier: Programming Language :: Python :: 3 :: Only
Classifier: Programming Language :: Python :: 3.8
Classifier: Programming Language :: Python :: 3.9
Classifier: Programming Language :: Python :: 3.10
Classifier: Topic :: Software Development :: Libraries
Requires-Python: >=3.8
License-File: LICENSE
Provides-Extra: bigquery
Requires-Dist: google-cloud-bigquery (==3.3.5) ; extra == 'bigquery'
Requires-Dist: google-cloud-bigquery-storage (==2.16.2) ; extra == 'bigquery'
